MANIFEST.in
README.md
setup.py
nlpre/__init__.py
nlpre/_version.py
nlpre/decaps_text.py
nlpre/dedash.py
nlpre/identify_parenthetical_phrases.py
nlpre/pos_tokenizer.py
nlpre/replace_acronyms.py
nlpre/replace_from_dictionary.py
nlpre/separate_reference.py
nlpre/separated_parenthesis.py
nlpre/spacy_init.py
nlpre/titlecaps.py
nlpre/token_replacement.py
nlpre/unidecoder.py
nlpre/url_replacement.py
nlpre.egg-info/PKG-INFO
nlpre.egg-info/SOURCES.txt
nlpre.egg-info/dependency_links.txt
nlpre.egg-info/requires.txt
nlpre.egg-info/top_level.txt
nlpre/Grammars/__init__.py
nlpre/Grammars/parenthesis_nester.py
nlpre/Grammars/reference_patterns.py
nlpre/dictionary/MeSH_two_word_lexicon.csv
nlpre/dictionary/__init__.py
nlpre/dictionary/english_wordlist.txt
nlpre/presets/__init__.py
nlpre/spacy_models/en_core_web_sm-2.1.0/accuracy.json
nlpre/spacy_models/en_core_web_sm-2.1.0/meta.json
nlpre/spacy_models/en_core_web_sm-2.1.0/tokenizer
nlpre/spacy_models/en_core_web_sm-2.1.0/ner/cfg
nlpre/spacy_models/en_core_web_sm-2.1.0/ner/model
nlpre/spacy_models/en_core_web_sm-2.1.0/ner/moves
nlpre/spacy_models/en_core_web_sm-2.1.0/parser/cfg
nlpre/spacy_models/en_core_web_sm-2.1.0/parser/model
nlpre/spacy_models/en_core_web_sm-2.1.0/parser/moves
nlpre/spacy_models/en_core_web_sm-2.1.0/tagger/cfg
nlpre/spacy_models/en_core_web_sm-2.1.0/tagger/model
nlpre/spacy_models/en_core_web_sm-2.1.0/tagger/tag_map
nlpre/spacy_models/en_core_web_sm-2.1.0/vocab/key2row
nlpre/spacy_models/en_core_web_sm-2.1.0/vocab/lexemes.bin
nlpre/spacy_models/en_core_web_sm-2.1.0/vocab/strings.json
nlpre/spacy_models/en_core_web_sm-2.1.0/vocab/vectors