Metadata-Version: 1.1
Name: nlpre
Version: 2.1.1
Summary: Natural Language Preprocessing (NLPre) utilities.
Home-page: https://github.com/NIHOPA/NLPre
Author: Travis Hoppe
Author-email: travis.hoppe+nlpre@gmail.com
License: CC0
Keywords: NLP
Platform: UNKNOWN
Classifier: Development Status :: 5 - Production/Stable
Classifier: Intended Audience :: Developers
Classifier: Intended Audience :: Science/Research
Classifier: Intended Audience :: Healthcare Industry
Classifier: Intended Audience :: Education
Classifier: Intended Audience :: Financial and Insurance Industry
Classifier: Natural Language :: English
Classifier: Topic :: Text Processing
Classifier: Topic :: Text Processing :: Filters
Classifier: Topic :: Utilities
Classifier: License :: OSI Approved :: MIT License
Classifier: Programming Language :: Python :: 3.6
